{"parent":"minecraft:item/generated","textures":{"layer0":"minecraft:item/totem_of_undying"},"overrides":[{"predicate":{"custom_model_data":10000},"model":"austotens:totem_velocidade"},{"predicate":{"custom_model_data":10001},"model":"austotens:totem_dano"},{"predicate":{"custom_model_data":10002},"model":"austotens:totem_velocidade_ataque"},{"predicate":{"custom_model_data":10003},"model":"austotens:totem_armadura"},{"predicate":{"custom_model_data":10004},"model":"austotens:totem_armadura_resistencia"},{"predicate":{"custom_model_data":10005},"model":"austotens:totem_sorte"},{"predicate":{"custom_model_data":10006},"model":"austotens:totem_repulsao"},{"predicate":{"custom_model_data":10007},"model":"item/totem_of_undying"}]}